{
  "title": "AI Tools for Urban Infill",
  "menu": {
    "brand": "S I G H T H O U N D",
    "brandHref": "/",
    "links": [
      { "text": "demo", "href": "/demo" },
      { "text": "sign up", "href": "/signup" }
    ]
  },
  "hero": {
    "eyebrow": "AI Tools for Urban Infill",
    "headline": "Build Smarter Infill Projects",
    "subHeadline": "AI-powered tools for small and mid-size developers. Simple to use, built to scale.",
    "image": "hero-placeholder.svg",
    "imageAlt": ""
  },
  "intro": "Use advanced AI to scout lots, generate concepts, and streamline approvals. Our lean approach keeps you focused on building homes, not wrangling data.",
  "features": [
    {
      "iconPath": "M12 2a10 10 0 1 0 0 20 10 10 0 0 0 0-20zm1 14h-2v-2H9v-2h2V9h2v3h2v2h-2v2z",
      "title": "Analyze",
      "text": "Instant site and zoning checks."
    },
    {
      "iconPath": "M3 13h8V3H3v10zm0 8h8v-6H3v6zm10 0h8V11h-8v10zm0-18v6h8V3h-8z",
      "title": "Design",
      "text": "Automated concepts ready to refine."
    },
    {
      "iconPath": "M4 3h7v7H4V3zm9 0h7v7h-7V3zM4 14h7v7H4v-7zm9 0h7v7h-7v-7z",
      "title": "Deliver",
      "text": "Permitting tasks handled for you."
    }
  ],
  "signup": {
    "action": "https://formspree.io/f/your-form-id",
    "label": "Email",
    "placeholder": "you@example.com",
    "buttonText": "Get Early Access",
    "thankYou": "Thanks—check your inbox!"
  }
}
